gitsummary/__init__.py
gitsummary/gitsummary.py
gitsummary_Timothy_W_Hilton-0.0.1.dist-info/LICENSE.txt
gitsummary_Timothy_W_Hilton-0.0.1.dist-info/METADATA
gitsummary_Timothy_W_Hilton-0.0.1.dist-info/WHEEL
gitsummary_Timothy_W_Hilton-0.0.1.dist-info/top_level.txt
gitsummary_Timothy_W_Hilton-0.0.1.dist-info/RECORD
