Metadata-Version: 2.1
Name: gitsummary-Timothy-W-Hilton
Version: 0.0.1
Summary: print a one-list summary of the current git repository, the current branch, and the hash for the current head
Home-page: https://github.com/Timothy-W-Hilton/gitsummary
Author: Timothy W. Hilton
Author-email: t.hilton@gns.cri.nz
Project-URL: Bug Tracker, https://github.com/Timothy-W-Hilton/gitsummary/issues
Classifier: Programming Language :: Python :: 3
Classifier: License :: OSI Approved :: MIT License
Classifier: Operating System :: OS Independent
Requires-Python: >=3.6
License-File: LICENSE.txt
